roxieapi/__init__.py
roxieapi/api.py
roxieapi/cadata/CableDatabase.py
roxieapi/cadata/CableDefinition.py
roxieapi/cadata/ConductorDefinition.py
roxieapi/cadata/Definition.py
roxieapi/cadata/FilamentDefinition.py
roxieapi/cadata/InsulationDefinition.py
roxieapi/cadata/QuenchDefinition.py
roxieapi/cadata/RemFitDefinition.py
roxieapi/cadata/StrandDefinition.py
roxieapi/cadata/TransientDefinition.py
roxieapi/cadata/__init__.py
roxieapi/commons/__init__.py
roxieapi/commons/jupyter_output.py
roxieapi/commons/roxie_constants.py
roxieapi/commons/roxie_style.py
roxieapi/commons/types.py
roxieapi/input/__init__.py
roxieapi/input/builder.py
roxieapi/input/parser.py
roxieapi/input/roxie_template.data.j2
roxieapi/input_builder/RoxieInputBuilder.py
roxieapi/input_builder/__init__.py
roxieapi/input_parser/RoxieInputParser.py
roxieapi/input_parser/__init__.py
roxieapi/notebooks/__init__.py
roxieapi/notebooks/roxie_report_template.ipynb
roxieapi/output/__init__.py
roxieapi/output/forces.py
roxieapi/output/parser.py
roxieapi/output/plots.py
roxieapi/output/xml_parse.py
roxieapi/tool_adapter/RoxieToolAdapter.py
roxieapi/tool_adapter/__init__.py
roxie_api-0.4.5.dist-info/METADATA
roxie_api-0.4.5.dist-info/WHEEL
roxie_api-0.4.5.dist-info/licenses/LICENSES/BSD-4-Clause.txt
roxie_api-0.4.5.dist-info/licenses/LICENSES/CC-BY-4.0.txt
roxie_api-0.4.5.dist-info/RECORD
