Metadata-Version: 2.4
Name: roxie-api
Version: 0.4.5
Summary: A Python API for ROXIE to build a model data input, modify cable database file, and control simulation with a tool adapter
License-Expression: MIT
License-File: LICENSES/BSD-4-Clause.txt
License-File: LICENSES/CC-BY-4.0.txt
Author: mmaciejewski
Author-email: michal.maciejewski@ief.ee.ethz.ch
Maintainer: Matthias Bonora
Maintainer-email: matthias.bonora@cern.ch
Requires-Python: >=3.9
Classifier: Intended Audience :: Education
Classifier: License :: OSI Approved :: MIT License
Classifier: Operating System :: OS Independent
Classifier: Programming Language :: Python :: 3
Classifier: Programming Language :: Python :: 3.9
Classifier: Programming Language :: Python :: 3.10
Classifier: Programming Language :: Python :: 3.11
Classifier: Programming Language :: Python :: 3.12
Classifier: Programming Language :: Python :: 3.13
Classifier: Programming Language :: Python :: 3.14
Provides-Extra: papermill
Provides-Extra: plots
Requires-Dist: Jinja2 (>=3.1.2,<4.0.0)
Requires-Dist: async-timeout (>=4.0.3,<5.0.0)
Requires-Dist: fastnumbers (>=5.1.0,<6.0.0)
Requires-Dist: ipython (>=8.2.0,<9.0.0) ; extra == "plots"
Requires-Dist: kaleido (==0.2.1) ; extra == "plots"
Requires-Dist: matplotlib (>=3.6.0,<4.0.0) ; extra == "plots"
Requires-Dist: mpld3 (>=0.5.9,<0.6.0) ; extra == "plots"
Requires-Dist: pandas (>=2.0.3,<3.0.0)
Requires-Dist: papermill (>=2.5.0,<3.0.0) ; extra == "papermill"
Requires-Dist: plotly (>=5.9.0,<6.0.0) ; extra == "plots"
Requires-Dist: pydantic (>=2,<3)
Requires-Dist: pyvista[all,trame] (>=0.46) ; extra == "plots"
Requires-Dist: requests (>=2.28.1,<3.0.0)
Requires-Dist: trame-matplotlib (>=2.0.2,<3.0.0) ; extra == "plots"
Project-URL: Documentation, https://roxie-api.docs.cern.ch/
Project-URL: Homepage, https://roxie.docs.cern.ch/
Project-URL: Repository, https://gitlab.cern.ch/roxie/roxie-api
